<?xml version="1.0" encoding="UTF-8"?>
<questionnaire>
	<person>
	  <user>kevin</user>
	  <firstName>Kevin</firstName>
	  <lastName>Beschorner</lastName>
	  <sex>m</sex>
	  <birthday>
	   	<day>2</day>
	    <month>1</month>
	  	<year>1987</year>
	  </birthday>
	  
	  <address>
	  	<postalcode>1010</postalcode>
	  	<city>Wien</city>
	  	<country>AUT</country>
	  </address>
	  <highesteducation>
	  	<self>TU Wien</self>
	  	<mother>Med Uni Wien</mother>
	  	<father>Matura</father>
	  </highesteducation>
	  <email>kevin17@gmx.at</email>
	  <location>Wien</location>
	  <interest>Java</interest>
	  
	  <newsletter>y</newsletter>
	</person>
</questionnaire>